{"nodes": [{"id": "c_users_shubh_desktop_ono_apps_web_src_lib_api_invoke_ts", "label": "_invoke.ts", "file_type": "code", "source_file": "C:\\Users\\shubh\\Desktop\\OnO\\apps\\web\\src\\lib\\api\\_invoke.ts", "source_location": "L1"}, {"id": "invoke_url", "label": "url()", "file_type": "code", "source_file": "C:\\Users\\shubh\\Desktop\\OnO\\apps\\web\\src\\lib\\api\\_invoke.ts", "source_location": "L3"}, {"id": "invoke_anon", "label": "anon()", "file_type": "code", "source_file": "C:\\Users\\shubh\\Desktop\\OnO\\apps\\web\\src\\lib\\api\\_invoke.ts", "source_location": "L4"}, {"id": "invoke_invoke", "label": "invoke()", "file_type": "code", "source_file": "C:\\Users\\shubh\\Desktop\\OnO\\apps\\web\\src\\lib\\api\\_invoke.ts", "source_location": "L11"}], "edges": [{"source": "c_users_shubh_desktop_ono_apps_web_src_lib_api_invoke_ts", "target": "types", "relation": "imports_from", "confidence": "EXTRACTED", "source_file": "C:\\Users\\shubh\\Desktop\\OnO\\apps\\web\\src\\lib\\api\\_invoke.ts", "source_location": "L1", "weight": 1.0}, {"source": "c_users_shubh_desktop_ono_apps_web_src_lib_api_invoke_ts", "target": "invoke_url", "relation": "contains", "confidence": "EXTRACTED", "source_file": "C:\\Users\\shubh\\Desktop\\OnO\\apps\\web\\src\\lib\\api\\_invoke.ts", "source_location": "L3", "weight": 1.0}, {"source": "c_users_shubh_desktop_ono_apps_web_src_lib_api_invoke_ts", "target": "invoke_anon", "relation": "contains", "confidence": "EXTRACTED", "source_file": "C:\\Users\\shubh\\Desktop\\OnO\\apps\\web\\src\\lib\\api\\_invoke.ts", "source_location": "L4", "weight": 1.0}, {"source": "c_users_shubh_desktop_ono_apps_web_src_lib_api_invoke_ts", "target": "invoke_invoke", "relation": "contains", "confidence": "EXTRACTED", "source_file": "C:\\Users\\shubh\\Desktop\\OnO\\apps\\web\\src\\lib\\api\\_invoke.ts", "source_location": "L11", "weight": 1.0}, {"source": "invoke_invoke", "target": "invoke_url", "relation": "calls", "confidence": "EXTRACTED", "source_file": "C:\\Users\\shubh\\Desktop\\OnO\\apps\\web\\src\\lib\\api\\_invoke.ts", "source_location": "L17", "weight": 1.0}, {"source": "invoke_invoke", "target": "invoke_anon", "relation": "calls", "confidence": "EXTRACTED", "source_file": "C:\\Users\\shubh\\Desktop\\OnO\\apps\\web\\src\\lib\\api\\_invoke.ts", "source_location": "L21", "weight": 1.0}]}